notion_export_prettify/args.py
notion_export_prettify/html_templator.py
notion_export_prettify/main.py
notion_export_prettify/notion_html_manipulator.py
notion_export_prettify/pdf_maker.py
notion_export_prettify/print_color.py
notion_export_prettify/resource_loader.py
notion_export_prettify-1.3.0.dist-info/LICENSE
notion_export_prettify-1.3.0.dist-info/METADATA
notion_export_prettify-1.3.0.dist-info/WHEEL
notion_export_prettify-1.3.0.dist-info/entry_points.txt
notion_export_prettify-1.3.0.dist-info/RECORD
