Metadata-Version: 2.1
Name: notion-export-prettify
Version: 1.3.0
Summary: 
Author: Fabre Lambeau
Author-email: fabre.lambeau@gmail.com
Requires-Python: >=3.11,<4.0
Classifier: Programming Language :: Python :: 3
Classifier: Programming Language :: Python :: 3.11
Classifier: Programming Language :: Python :: 3.12
Requires-Dist: beautifulsoup4 (>=4.12.3,<5.0.0)
Requires-Dist: colorama (>=0.4.6,<0.5.0)
Requires-Dist: configargparse (>=1.7,<2.0)
Requires-Dist: jinja2 (>=3.1.3,<4.0.0)
Requires-Dist: playwright (>=1.42.0,<2.0.0)
Requires-Dist: pymupdf (>=1.24.0,<2.0.0)
